acstools/__init__.py
acstools/acs2d.py
acstools/acs_destripe.py
acstools/acs_destripe_plus.py
acstools/acsccd.py
acstools/acscte.py
acstools/acscteforwardmodel.py
acstools/acsphotcte.py
acstools/acsrej.py
acstools/acssum.py
acstools/acszpt.py
acstools/calacs.py
acstools/findsat_mrt.py
acstools/focus_diverse_epsfs.py
acstools/polarization_tools.py
acstools/satdet.py
acstools/utils_calib.py
acstools/utils_findsat_mrt.py
acstools/version.py
acstools/data/polarizer_tables.yaml
acstools/data/rt_line_kernel_width15.fits
acstools/data/rt_line_kernel_width3.fits
acstools/data/rt_line_kernel_width7.fits
acstools/tests/__init__.py
acstools/tests/helpers.py
acstools/tests/test_polarization.py
acstools/tests/test_wfc_destripe.py
acstools/tests/test_wfc_findsat_mrt.py
acstools/tests/test_wfc_satdet.py
acstools/tests/data/input/ja0x03ojq_flt.fits
acstools/tests/data/input/jb5g05ubq_flt.fits
acstools/tests/data/input/jc2z03cvq_blv_tmp.fits
acstools/tests/data/input/jc5001soq_flt.fits
acstools/tests/data/input/jc8m10syq_flc.fits
acstools/tests/data/input/jc8m32j5q_flc.fits
acstools/tests/data/input/jc8o04ghq_flt.fits
acstools/tests/data/input/jc8o04ghq_mask1.fits
acstools/tests/data/input/jc8o04ghq_mask2.fits
acstools/tests/data/truth/ja0x03ojq_flt_ref.fits
acstools/tests/data/truth/jb5g05ubq_flt_ref.fits
acstools/tests/data/truth/jc2z03cvq_blv_tmp_ref.fits
acstools/tests/data/truth/jc5001soq_flt_ref.fits
acstools/tests/data/truth/jc8m10syq_flc_ref.fits
acstools/tests/data/truth/jc8m32j5q_flc_mask_ref.fits
acstools/tests/data/truth/jc8o04ghq_flt_ref.fits
acstools-3.7.2.dist-info/LICENSE.md
acstools-3.7.2.dist-info/METADATA
acstools-3.7.2.dist-info/WHEEL
acstools-3.7.2.dist-info/entry_points.txt
acstools-3.7.2.dist-info/top_level.txt
acstools-3.7.2.dist-info/RECORD
